crashreport.py
crashreport-1.1.2.dist-info/LICENSE
crashreport-1.1.2.dist-info/METADATA
crashreport-1.1.2.dist-info/WHEEL
crashreport-1.1.2.dist-info/top_level.txt
crashreport-1.1.2.dist-info/RECORD
